.DS_Store
.gitignore
CHANGES.txt
MANIFEST
MANIFEST.in
README.md
README.txt
latex2markdown-bbsmp.py
setup.py
config/__init__.py
config/charmap.xml
config/converted_latex_sample.md
config/latex_sample.tex
latex2markdown_bbsmp.egg-info/PKG-INFO
latex2markdown_bbsmp.egg-info/SOURCES.txt
latex2markdown_bbsmp.egg-info/dependency_links.txt
latex2markdown_bbsmp.egg-info/requires.txt
latex2markdown_bbsmp.egg-info/top_level.txt