Metadata-Version: 1.1
Name: latex2markdown-bbsmp
Version: 0.0.4.0
Summary: Forked from Andrew's masterpiece：https://github.com/ajtulloch/LaTeX2Markdown,  An AMS-LaTeX compatible converter that maps a subset of LaTeX to Markdown/MathJaX.
Home-page: https://github.com/bbsmp/LaTeX2Markdown.git
Author: PengMo
Author-email: qinmetec@163.com
License: UNKNOWN
Platform: UNKNOWN
Classifier: Development Status :: 3 - Alpha
Classifier: Environment :: Console
Classifier: Programming Language :: Python
Classifier: Topic :: Scientific/Engineering :: Mathematics
Classifier: Topic :: Software Development :: Documentation
Classifier: Topic :: Text Processing :: Markup
Classifier: Topic :: Text Processing :: Markup :: LaTeX
Classifier: Topic :: Text Processing :: Markup :: HTML
